{"game":{"id":2719,"team_season_id_home":214,"team_season_id_away":215,"status_id":101,"score_home":20,"score_away":18,"live":null,"reg_season":true,"lock":false,"start_timestamp":"2021-08-14T18:00:00.000Z","start_timezone":"EDT","start_time_tbd":null,"aw_section":"week-11","score_times_home":[1,218,393,601,691,714,1176,1294,1419,1432,1517,1824,1872,1943,2139,2227,2385,2508,2573,2602,2857],"score_times_away":[1,38,115,349,466,553,654,790,898,996,1263,1360,1440,1468,1562,1721,1844,2001,2331],"ext_game_id":"2021-08-14-ATL-RAL","update_timestamp":"2021-08-15T01:25:56.835Z","team_season_home":{"id":214,"team_id":18,"season_id":12,"division_id":5,"city":"Raleigh","abbrev":"RAL","ulti_analytics_ext_id":null,"final_standing":null,"team":{"id":18,"name":"Flyers","ext_team_id":"flyers"}},"team_season_away":{"id":215,"team_id":1,"season_id":12,"division_id":5,"city":"Atlanta","abbrev":"ATL","ulti_analytics_ext_id":null,"final_standing":null,"team":{"id":1,"name":"Hustle","ext_team_id":"hustle"}}},"rostersHome":[{"id":8815,"team_season_id":214,"player_id":77,"jersey_number":"26","active":true,"player":{"id":77,"first_name":"Allan","last_name":"Laviolette","ext_player_id":"alaviolet"}},{"id":8818,"team_season_id":214,"player_id":107,"jersey_number":"30","active":true,"player":{"id":107,"first_name":"Andrew","last_name":"McKelvey","ext_player_id":"amckelvey"}},{"id":8828,"team_season_id":214,"player_id":509,"jersey_number":"84","active":true,"player":{"id":509,"first_name":"David","last_name":"Richardson","ext_player_id":"drichards1"}},{"id":8810,"team_season_id":214,"player_id":752,"jersey_number":"20","active":true,"player":{"id":752,"first_name":"Jacob","last_name":"Fairfax","ext_player_id":"jfairfax"}},{"id":8802,"team_season_id":214,"player_id":755,"jersey_number":"9","active":true,"player":{"id":755,"first_name":"Jacob","last_name":"Mouw","ext_player_id":"jmouw"}},{"id":8800,"team_season_id":214,"player_id":831,"jersey_number":"7","active":true,"player":{"id":831,"first_name":"Jeff","last_name":"Nordgren","ext_player_id":"jnordgren"}},{"id":8805,"team_season_id":214,"player_id":888,"jersey_number":"12","active":true,"player":{"id":888,"first_name":"Joey","last_name":"Cretella","ext_player_id":"jcretella"}},{"id":8829,"team_season_id":214,"player_id":971,"jersey_number":"99","active":true,"player":{"id":971,"first_name":"Josh","last_name":"Hartzog","ext_player_id":"jhartzog"}},{"id":8796,"team_season_id":214,"player_id":994,"jersey_number":"1","active":true,"player":{"id":994,"first_name":"Justin","last_name":"Allen","ext_player_id":"jallen"}},{"id":8825,"team_season_id":214,"player_id":1010,"jersey_number":"52","active":true,"player":{"id":1010,"first_name":"Kamron","last_name":"Daftari","ext_player_id":"kdaftari"}},{"id":8807,"team_season_id":214,"player_id":1078,"jersey_number":"14","active":true,"player":{"id":1078,"first_name":"Kiron","last_name":"Allen","ext_player_id":"kallen"}},{"id":8814,"team_season_id":214,"player_id":1405,"jersey_number":"24","active":true,"player":{"id":1405,"first_name":"Noah","last_name":"Saul","ext_player_id":"nsaul"}},{"id":8806,"team_season_id":214,"player_id":1631,"jersey_number":"13","active":true,"player":{"id":1631,"first_name":"Shane","last_name":"Sisco","ext_player_id":"ssisco"}},{"id":8797,"team_season_id":214,"player_id":1643,"jersey_number":"2","active":true,"player":{"id":1643,"first_name":"Sol","last_name":"Yanuck","ext_player_id":"syanuck"}},{"id":8801,"team_season_id":214,"player_id":1705,"jersey_number":"8","active":true,"player":{"id":1705,"first_name":"Terrence","last_name":"Mitchell","ext_player_id":"tmitchell"}},{"id":8824,"team_season_id":214,"player_id":1724,"jersey_number":"51","active":true,"player":{"id":1724,"first_name":"Tim","last_name":"McAllister","ext_player_id":"tmcallist"}},{"id":8820,"team_season_id":214,"player_id":1769,"jersey_number":"34","active":true,"player":{"id":1769,"first_name":"Tristan","last_name":"Green","ext_player_id":"tgreen"}},{"id":8808,"team_season_id":214,"player_id":2201,"jersey_number":"15","active":true,"player":{"id":2201,"first_name":"Eric","last_name":"Taylor","ext_player_id":"etaylor"}},{"id":8803,"team_season_id":214,"player_id":2202,"jersey_number":"10","active":true,"player":{"id":2202,"first_name":"Henry","last_name":"Fisher","ext_player_id":"hfisher"}},{"id":9328,"team_season_id":214,"player_id":2222,"jersey_number":"4","active":true,"player":{"id":2222,"first_name":"Seth","last_name":"Weaver","ext_player_id":"sweaver"}},{"id":8817,"team_season_id":214,"player_id":2342,"jersey_number":"29","active":true,"player":{"id":2342,"first_name":"Grayson","last_name":"Sanner","ext_player_id":"gsanner"}},{"id":9333,"team_season_id":214,"player_id":2357,"jersey_number":"31","active":true,"player":{"id":2357,"first_name":"Connor","last_name":"Russell","ext_player_id":"crussell"}},{"id":8804,"team_season_id":214,"player_id":2396,"jersey_number":"11","active":true,"player":{"id":2396,"first_name":"Elijah","last_name":"Long","ext_player_id":"elong"}},{"id":8812,"team_season_id":214,"player_id":2397,"jersey_number":"22","active":true,"player":{"id":2397,"first_name":"Bailey","last_name":"LaBerteaux","ext_player_id":"blabertea"}},{"id":8813,"team_season_id":214,"player_id":2398,"jersey_number":"23","active":true,"player":{"id":2398,"first_name":"Walker","last_name":"Matthews","ext_player_id":"wmatthews"}},{"id":9542,"team_season_id":214,"player_id":2402,"jersey_number":"19","active":true,"player":{"id":2402,"first_name":"Ethan","last_name":"Bolthouse","ext_player_id":"ebolthous"}},{"id":8827,"team_season_id":214,"player_id":2403,"jersey_number":"80","active":true,"player":{"id":2403,"first_name":"Matt","last_name":"Gouchoe-Hanas","ext_player_id":"mgouchoeh"}},{"id":9329,"team_season_id":214,"player_id":2563,"jersey_number":"5","active":true,"player":{"id":2563,"first_name":"Vincent","last_name":"Calderon","ext_player_id":"vcalderon"}},{"id":9330,"team_season_id":214,"player_id":2564,"jersey_number":"16","active":true,"player":{"id":2564,"first_name":"Anders","last_name":"Juengst","ext_player_id":"ajuengst"}},{"id":9334,"team_season_id":214,"player_id":2566,"jersey_number":"50","active":true,"player":{"id":2566,"first_name":"Matthew","last_name":"Mcknight","ext_player_id":"mmcknight"}},{"id":9332,"team_season_id":214,"player_id":2565,"jersey_number":"28","active":true,"player":{"id":2565,"first_name":"Ethan","last_name":"Bloodworth","ext_player_id":"ebloodwor"}},{"id":9335,"team_season_id":214,"player_id":2567,"jersey_number":"76","active":true,"player":{"id":2567,"first_name":"Trevor","last_name":"Lynch","ext_player_id":"tlynch"}},{"id":9543,"team_season_id":214,"player_id":2668,"jersey_number":"18","active":true,"player":{"id":2668,"first_name":"Suraj","last_name":"Madiraju","ext_player_id":"smadiraju"}},{"id":9544,"team_season_id":214,"player_id":2669,"jersey_number":"43","active":true,"player":{"id":2669,"first_name":"Marc","last_name":"Rovner","ext_player_id":"mrovner"}},{"id":9331,"team_season_id":214,"player_id":2781,"jersey_number":"27","active":true,"player":{"id":2781,"first_name":"Alex","last_name":"Davis","ext_player_id":"adavis4"}}],"tsgHome":{"id":259,"teamSeasonId":214,"gameId":2719,"rosterIds":[8797,9328,8801,8804,8803,8805,8808,8810,9330,8814,8815,9331,9332,9333,9334,8824,9335,8827,8828,8829],"valid":true,"startOnOffense":false,"events":"[{\"t\":2,\"l\":[8808,8828,9331,9332,8824,8804,8814]},{\"t\":3,\"r\":8824,\"x\":0,\"y\":80,\"ms\":6029},{\"t\":11},{\"t\":21,\"s\":682},{\"t\":1,\"l\":[8810,8803,8827,9330,8815,9334,8797]},{\"t\":20,\"r\":8827,\"x\":-2.39,\"y\":30.81},{\"t\":20,\"r\":8797,\"x\":-12.49,\"y\":42.06},{\"t\":20,\"r\":8815,\"x\":-22.72,\"y\":54},{\"t\":20,\"r\":8797,\"x\":-17.33,\"y\":42.27},{\"t\":20,\"r\":8827,\"x\":-4.57,\"y\":45.13},{\"t\":20,\"r\":8797,\"x\":-8.94,\"y\":44.11},{\"t\":20,\"r\":8827,\"x\":-2.39,\"y\":49.56},{\"t\":8,\"x\":12.54,\"y\":104.59},{\"t\":21,\"s\":605},{\"t\":1,\"l\":[8810,8827,8815,8801,8808,8797,8804]},{\"t\":20,\"r\":8797,\"x\":7.77,\"y\":34.36},{\"t\":20,\"r\":8827,\"x\":-0.14,\"y\":32.04},{\"t\":20,\"r\":8797,\"x\":7.36,\"y\":35.86},{\"t\":20,\"r\":8808,\"q\":1,\"x\":18.2,\"y\":63.34},{\"t\":20,\"r\":8810,\"x\":-13.78,\"y\":63.13},{\"t\":20,\"r\":8827,\"x\":-2.05,\"y\":71.86},{\"t\":20,\"r\":8797,\"x\":-2.32,\"y\":60.74},{\"t\":20,\"r\":8804,\"x\":0.27,\"y\":71.18},{\"t\":20,\"r\":8797,\"x\":0.13,\"y\":74.25},{\"t\":20,\"r\":8804,\"x\":7.97,\"y\":71.72},{\"t\":20,\"r\":8797,\"x\":0.68,\"y\":70.29},{\"t\":20,\"r\":8804,\"x\":-3.28,\"y\":72.81},{\"t\":20,\"r\":8827,\"x\":-14.94,\"y\":78.4},{\"t\":20,\"r\":8804,\"x\":-11.05,\"y\":73.77},{\"t\":20,\"r\":8827,\"x\":-9.35,\"y\":90.88},{\"t\":12},{\"t\":20,\"r\":8797,\"x\":-3.82,\"y\":93.81},{\"t\":22,\"r\":8810,\"x\":17.18,\"y\":114.4,\"s\":502},{\"t\":2,\"l\":[9331,9335,8805,8829,8814,9328,9333]},{\"t\":3,\"r\":8829,\"x\":-0.55,\"y\":100.77,\"ms\":6327},{\"t\":9},{\"t\":20,\"r\":8814,\"x\":-26.67,\"y\":55.29},{\"t\":20,\"r\":9328,\"x\":-24.97,\"y\":75.13},{\"t\":20,\"r\":9335,\"x\":-14.12,\"y\":78.13},{\"t\":20,\"r\":8814,\"x\":-8.33,\"y\":72.95},{\"t\":20,\"r\":8805,\"x\":24.55,\"y\":92.93},{\"t\":20,\"r\":8814,\"x\":19.43,\"y\":88.22},{\"t\":20,\"r\":9333,\"x\":0.61,\"y\":89.59},{\"t\":8,\"x\":-26.67,\"y\":102.06},{\"t\":13},{\"t\":21,\"s\":371},{\"t\":1,\"l\":[8810,8803,8827,9330,8801,8797,8804]},{\"t\":20,\"r\":8827,\"x\":-19.99,\"y\":19.99},{\"t\":20,\"r\":8797,\"x\":-6.89,\"y\":27.47},{\"t\":20,\"r\":9330,\"x\":12.75,\"y\":39.95},{\"t\":20,\"r\":8797,\"x\":5.38,\"y\":45},{\"t\":20,\"r\":8801,\"x\":-6.28,\"y\":45.47},{\"t\":20,\"r\":8804,\"x\":-13.65,\"y\":59.99},{\"t\":20,\"r\":8810,\"x\":-14.26,\"y\":70.56},{\"t\":20,\"r\":8803,\"x\":-14.87,\"y\":84.4},{\"t\":20,\"r\":8797,\"x\":-15.42,\"y\":93.4},{\"t\":22,\"r\":9330,\"x\":-1.16,\"y\":105.88,\"s\":327},{\"t\":2,\"l\":[8824,8805,8828,8814,9332,8804,8808]},{\"t\":3,\"r\":8824,\"x\":-19.31,\"y\":104.31,\"ms\":6703},{\"t\":5,\"r\":8808,\"h\":1},{\"t\":20,\"r\":8814,\"x\":-26.67,\"y\":20},{\"t\":19,\"r\":9332,\"x\":-8.67,\"y\":27.34},{\"t\":43},{\"t\":40,\"l\":[8824,8805,8828,8814,8804,8808,9328]},{\"t\":21,\"s\":254},{\"t\":1,\"l\":[8810,8827,8815,9334,8808,8797,8804]},{\"t\":20,\"r\":8827,\"x\":0.88,\"y\":15.34},{\"t\":20,\"r\":8797,\"x\":1.02,\"y\":34.9},{\"t\":20,\"r\":8827,\"x\":9.07,\"y\":30.54},{\"t\":20,\"r\":8804,\"x\":15.95,\"y\":38.45},{\"t\":20,\"r\":8797,\"x\":-4.3,\"y\":26.86},{\"t\":20,\"r\":8815,\"x\":2.25,\"y\":59.59},{\"t\":20,\"r\":8808,\"x\":-6.28,\"y\":68.31},{\"t\":20,\"r\":8827,\"x\":11.73,\"y\":62.31},{\"t\":20,\"r\":8797,\"x\":0.81,\"y\":56.38},{\"t\":20,\"r\":8827,\"x\":4.29,\"y\":60.74},{\"t\":20,\"r\":8797,\"x\":6.06,\"y\":63.4},{\"t\":12},{\"t\":8,\"x\":5.86,\"y\":76.77},{\"t\":21,\"s\":167},{\"t\":1,\"l\":[8797,8810,8803,8815,8801,9330,8827]},{\"t\":20,\"r\":8827,\"x\":-13.3,\"y\":29.11},{\"t\":20,\"r\":8797,\"x\":-0.14,\"y\":25.77},{\"t\":20,\"r\":8810,\"x\":12.54,\"y\":30.95},{\"t\":20,\"r\":8797,\"x\":9.2,\"y\":29.11},{\"t\":20,\"r\":8803,\"x\":11.93,\"y\":40.02},{\"t\":20,\"r\":8797,\"x\":3.95,\"y\":27.75},{\"t\":20,\"r\":8827,\"x\":-7.98,\"y\":30.68},{\"t\":20,\"r\":8803,\"x\":-15.35,\"y\":45.2},{\"t\":20,\"r\":8810,\"x\":-4.37,\"y\":51.4},{\"t\":20,\"r\":8801,\"h\":1,\"x\":19.43,\"y\":94.36},{\"t\":22,\"r\":8803,\"x\":19.16,\"y\":103.36,\"s\":119},{\"t\":2,\"l\":[9328,8814,9333,9331,8805,9335,8829]},{\"t\":3,\"r\":8829,\"x\":-12.14,\"y\":100,\"ms\":8626},{\"t\":21,\"s\":66},{\"t\":1,\"l\":[8810,8803,8827,8808,8797,8804,8815]},{\"t\":20,\"r\":8827,\"x\":8.11,\"y\":10.9},{\"t\":20,\"r\":8797,\"x\":1.09,\"y\":30.34},{\"t\":20,\"r\":8827,\"x\":-3.14,\"y\":27.2},{\"t\":20,\"r\":8804,\"x\":7.29,\"y\":31.15},{\"t\":20,\"r\":8827,\"x\":0,\"y\":26.79},{\"t\":20,\"r\":8797,\"x\":-9.83,\"y\":33.68},{\"t\":20,\"r\":8827,\"x\":-3.76,\"y\":34.22},{\"t\":20,\"r\":8804,\"x\":5.59,\"y\":34.29},{\"t\":20,\"r\":8810,\"x\":10.36,\"y\":49.56},{\"t\":20,\"r\":8815,\"x\":10.7,\"y\":80.38},{\"t\":22,\"r\":8803,\"h\":1,\"x\":10.29,\"y\":114.34,\"s\":29},{\"t\":2,\"l\":[9335,8824,8829,8814,9328,9331,8828]},{\"t\":4,\"r\":8824,\"x\":0,\"y\":80},{\"t\":9},{\"t\":20,\"r\":8814,\"x\":11.25,\"y\":49.49},{\"t\":14,\"s\":19},{\"t\":41,\"l\":[8827,8815,8803,8814,8808,8797,8810]},{\"t\":20,\"r\":8797,\"x\":11.25,\"y\":49.49},{\"t\":20,\"r\":8827,\"x\":-9.96,\"y\":64.56},{\"t\":20,\"r\":8814,\"x\":-16.51,\"y\":68.11},{\"t\":20,\"r\":8827,\"x\":-7.1,\"y\":64.56},{\"t\":20,\"r\":8797,\"x\":3.61,\"y\":66.27},{\"t\":22,\"r\":8815,\"h\":1,\"x\":20.93,\"y\":103.02,\"s\":6},{\"t\":2,\"l\":[8803,8829,8810,9335,8828,8824,8815]},{\"t\":3,\"r\":8829,\"x\":-7.51,\"y\":100,\"ms\":7215},{\"t\":5,\"r\":8824},{\"t\":23},{\"t\":1,\"l\":[8810,8803,8827,9330,9334,8801,8797]},{\"t\":20,\"r\":8797,\"x\":9.13,\"y\":18},{\"t\":20,\"r\":9334,\"x\":9.68,\"y\":29.59},{\"t\":20,\"r\":8810,\"x\":12.27,\"y\":39.34},{\"t\":20,\"r\":9334,\"x\":7.43,\"y\":48.54},{\"t\":20,\"r\":8797,\"x\":2.72,\"y\":45.95},{\"t\":20,\"r\":9330,\"x\":-11.8,\"y\":53.79},{\"t\":8,\"x\":-12.35,\"y\":67.02},{\"t\":15,\"s\":670},{\"t\":40,\"l\":[8824,8828,8808,8814,8804,9331,9332]},{\"t\":21,\"s\":650},{\"t\":1,\"l\":[8810,8827,8815,8801,8808,8797,8804]},{\"t\":20,\"r\":8808,\"x\":-26.67,\"y\":79.56},{\"t\":20,\"r\":8810,\"x\":19.16,\"y\":64.15},{\"t\":20,\"r\":8797,\"x\":19.16,\"y\":63.34},{\"t\":20,\"r\":8827,\"x\":4.16,\"y\":58.36},{\"t\":20,\"r\":8797,\"x\":7.97,\"y\":58.02},{\"t\":20,\"r\":8808,\"x\":1.15,\"y\":85.09},{\"t\":20,\"r\":8804,\"x\":-13.58,\"y\":85.15},{\"t\":19,\"r\":8801,\"x\":-8.94,\"y\":96.47},{\"t\":15,\"s\":577},{\"t\":40,\"l\":[8814,8828,8805,9335,9328,8829,9333]},{\"t\":11},{\"t\":21,\"s\":542},{\"t\":1,\"l\":[8810,8803,8827,9330,8815,8801,8797]},{\"t\":20,\"r\":8797,\"x\":3.27,\"y\":25.29},{\"t\":20,\"r\":8827,\"x\":0.4,\"y\":31.63},{\"t\":20,\"r\":8803,\"x\":14.39,\"y\":46.15},{\"t\":20,\"r\":9330,\"x\":14.73,\"y\":56.79},{\"t\":20,\"r\":8803,\"x\":6.95,\"y\":57.2},{\"t\":20,\"r\":8827,\"x\":15.27,\"y\":57.54},{\"t\":20,\"r\":8797,\"x\":4.77,\"y\":54.68},{\"t\":12},{\"t\":20,\"r\":8803,\"x\":8.25,\"y\":75.47},{\"t\":20,\"r\":8797,\"x\":-1.03,\"y\":67.22},{\"t\":20,\"r\":8815,\"x\":-16.85,\"y\":69.2},{\"t\":20,\"r\":8797,\"x\":-8.33,\"y\":65.65},{\"t\":20,\"r\":8815,\"x\":2.04,\"y\":66.81},{\"t\":8,\"x\":12.34,\"y\":68.31},{\"t\":21,\"s\":444},{\"t\":1,\"l\":[8803,8827,8815,9334,8808,8797,8804]},{\"t\":20,\"r\":8827,\"x\":12.61,\"y\":24.4},{\"t\":20,\"r\":8797,\"x\":1.9,\"y\":24.54},{\"t\":20,\"r\":8827,\"x\":9.27,\"y\":26.18},{\"t\":20,\"r\":8797,\"x\":-3.55,\"y\":25.09},{\"t\":20,\"r\":8827,\"x\":4.63,\"y\":25.56},{\"t\":20,\"r\":8804,\"x\":14.32,\"y\":26.45},{\"t\":20,\"r\":8808,\"x\":22.77,\"y\":39.06},{\"t\":8,\"x\":15.68,\"y\":93.68},{\"t\":13},{\"t\":5,\"r\":8803,\"h\":1},{\"t\":42},{\"t\":41,\"l\":[8827,8815,9334,8808,8797,8804,8810]},{\"t\":20,\"r\":8797,\"x\":-9.83,\"y\":19.99},{\"t\":20,\"r\":8827,\"x\":-4.85,\"y\":10.9},{\"t\":20,\"r\":8804,\"x\":6.82,\"y\":10.5},{\"t\":20,\"r\":8797,\"x\":12.95,\"y\":13.49},{\"t\":20,\"r\":9334,\"x\":-3.82,\"y\":19.99},{\"t\":20,\"r\":8810,\"x\":-24.56,\"y\":50.18},{\"t\":20,\"r\":8827,\"x\":-12.69,\"y\":30.4},{\"t\":20,\"r\":8797,\"x\":-1.03,\"y\":30.06},{\"t\":20,\"r\":8827,\"x\":-5.94,\"y\":29.45},{\"t\":20,\"r\":8797,\"x\":-0.62,\"y\":28.15},{\"t\":20,\"r\":8815,\"x\":1.09,\"y\":48.4},{\"t\":20,\"r\":9334,\"x\":-3.14,\"y\":55.9},{\"t\":20,\"r\":8797,\"x\":3.81,\"y\":55.49},{\"t\":20,\"r\":8810,\"x\":5.66,\"y\":70.29},{\"t\":20,\"r\":8797,\"x\":7.77,\"y\":67.56},{\"t\":20,\"r\":8808,\"x\":19.36,\"y\":78.95},{\"t\":20,\"r\":8797,\"x\":13.64,\"y\":74.79},{\"t\":20,\"r\":8827,\"x\":4.29,\"y\":72.81},{\"t\":20,\"r\":9334,\"x\":9.34,\"y\":83.52},{\"t\":12},{\"t\":22,\"r\":8804,\"x\":-13.58,\"y\":102.54,\"s\":264},{\"t\":2,\"l\":[8824,8828,9331,9332,8814,9330,8808]},{\"t\":3,\"r\":8824,\"x\":8.59,\"y\":100,\"ms\":6324},{\"t\":9},{\"t\":20,\"r\":8824,\"x\":-21.62,\"y\":59.31},{\"t\":20,\"r\":8814,\"x\":-8.46,\"y\":57.34},{\"t\":20,\"r\":8808,\"x\":-8.67,\"y\":74.86},{\"t\":20,\"r\":8814,\"x\":-10.17,\"y\":68.79},{\"t\":20,\"r\":8808,\"x\":-6.76,\"y\":63.61},{\"t\":20,\"r\":9330,\"x\":10.57,\"y\":78.54},{\"t\":20,\"r\":8808,\"x\":9.88,\"y\":86.18},{\"t\":8,\"x\":-7.71,\"y\":94.84},{\"t\":21,\"s\":177},{\"t\":1,\"l\":[8810,8803,8827,8815,8801,8797,9334]},{\"t\":20,\"r\":8827,\"x\":3.95,\"y\":19.99},{\"t\":20,\"r\":8797,\"x\":3.47,\"y\":26.31},{\"t\":20,\"r\":8815,\"x\":-12.14,\"y\":35.11},{\"t\":20,\"r\":8803,\"x\":-6.55,\"y\":48.61},{\"t\":20,\"r\":9334,\"x\":-6.55,\"y\":59.38},{\"t\":22,\"r\":8803,\"h\":1,\"x\":0.4,\"y\":109.02,\"s\":146},{\"t\":2,\"l\":[9335,8829,8824,8828,8804,9331,8814]},{\"t\":3,\"r\":8814,\"x\":-26.26,\"y\":59.45,\"ms\":12663},{\"t\":11},{\"t\":11},{\"t\":21,\"s\":80},{\"t\":1,\"l\":[8810,8827,8815,9334,8808,8797,8804]},{\"t\":20,\"r\":8827,\"x\":7.43,\"y\":14.11},{\"t\":20,\"r\":8797,\"x\":0.88,\"y\":24.81},{\"t\":20,\"r\":8804,\"x\":-8.67,\"y\":34.7},{\"t\":20,\"r\":8815,\"x\":-7.78,\"y\":49.49},{\"t\":20,\"r\":8804,\"x\":-8.53,\"y\":44.31},{\"t\":20,\"r\":8827,\"x\":5.45,\"y\":39.68},{\"t\":20,\"r\":8804,\"x\":4.36,\"y\":48.74},{\"t\":20,\"r\":8810,\"x\":8.66,\"y\":59.93},{\"t\":20,\"r\":8815,\"x\":11.73,\"y\":61.29},{\"t\":20,\"r\":8810,\"x\":12.07,\"y\":53.79},{\"t\":20,\"r\":8827,\"x\":1.9,\"y\":50.38},{\"t\":20,\"r\":9334,\"x\":-6.69,\"y\":46.09},{\"t\":20,\"r\":8827,\"x\":3.13,\"y\":36.27},{\"t\":20,\"r\":8804,\"x\":17.86,\"y\":45},{\"t\":20,\"r\":8815,\"x\":-7.44,\"y\":79.9},{\"t\":22,\"r\":8808,\"h\":1,\"x\":16.36,\"y\":107.86,\"s\":21},{\"t\":2,\"l\":[8828,8814,9335,8829,9328,8810,8824]},{\"t\":3,\"r\":8814,\"x\":13.84,\"y\":96.81,\"ms\":8620},{\"t\":9},{\"t\":20,\"r\":8814,\"x\":10.5,\"y\":80.79},{\"t\":20,\"r\":8824,\"x\":2.93,\"y\":84.81},{\"t\":20,\"r\":8814,\"x\":3.61,\"y\":95.65},{\"t\":22,\"r\":8828,\"x\":2.79,\"y\":107.59,\"s\":8},{\"t\":2,\"l\":[8815,8803,8824,8810,8829,9335,8828]},{\"t\":3,\"r\":8829,\"x\":9.75,\"y\":100.9,\"ms\":6672},{\"t\":21,\"s\":0},{\"t\":24},{\"t\":2,\"l\":[9328,8814,8805,9332,8828,8824,8808]},{\"t\":3,\"r\":8814,\"x\":-7.23,\"y\":91.29,\"ms\":5527},{\"t\":21,\"s\":692},{\"t\":1,\"l\":[8803,8827,9330,8815,9334,8801,8797]},{\"t\":20,\"r\":9334,\"x\":-21.15,\"y\":31.15},{\"t\":20,\"r\":8797,\"x\":1.29,\"y\":28.5},{\"t\":20,\"r\":8815,\"x\":14.73,\"y\":35.65},{\"t\":20,\"r\":9330,\"x\":19.5,\"y\":44.31},{\"t\":20,\"r\":8803,\"x\":20.11,\"y\":60.95},{\"t\":20,\"r\":8801,\"x\":20.11,\"y\":70.84},{\"t\":20,\"r\":8827,\"x\":2.45,\"y\":64.84},{\"t\":20,\"r\":8797,\"x\":-10.24,\"y\":65.59},{\"t\":20,\"r\":8815,\"x\":-19.65,\"y\":74.45},{\"t\":20,\"r\":8797,\"x\":-6.55,\"y\":70.77},{\"t\":20,\"r\":8815,\"x\":3.81,\"y\":74.79},{\"t\":22,\"r\":9334,\"h\":1,\"x\":-20.94,\"y\":104.38,\"s\":643},{\"t\":2,\"l\":[8824,8829,9335,9333,8808,9331,8804]},{\"t\":3,\"r\":8824,\"x\":0,\"y\":80,\"ms\":7326},{\"t\":21,\"s\":598},{\"t\":1,\"l\":[8810,8827,8815,9334,8808,8797,8804]},{\"t\":20,\"r\":8827,\"x\":-9.35,\"y\":25.15},{\"t\":20,\"r\":8797,\"x\":-1.78,\"y\":35.18},{\"t\":20,\"r\":8810,\"x\":2.65,\"y\":57.4},{\"t\":20,\"r\":8797,\"x\":-0.55,\"y\":55.02},{\"t\":20,\"r\":8810,\"x\":5.04,\"y\":61.63},{\"t\":20,\"r\":8827,\"x\":3.95,\"y\":55.09},{\"t\":20,\"r\":8804,\"x\":-13.92,\"y\":56.04},{\"t\":20,\"r\":8810,\"x\":-18.62,\"y\":67.22},{\"t\":20,\"r\":8797,\"x\":-7.51,\"y\":68.52},{\"t\":8,\"x\":-19.99,\"y\":105.75},{\"t\":13},{\"t\":15,\"s\":509},{\"t\":40,\"l\":[8805,8824,9332,8828,9328,8814,8808]},{\"t\":11},{\"t\":21,\"s\":439},{\"t\":1,\"l\":[8810,8803,8827,9330,8815,9334,8797]},{\"t\":20,\"r\":8827,\"x\":14.11,\"y\":25.49},{\"t\":20,\"r\":8797,\"x\":-1.1,\"y\":28.7},{\"t\":20,\"r\":8803,\"x\":-16.71,\"y\":43.97},{\"t\":8,\"x\":-14.05,\"y\":107.18},{\"t\":18},{\"t\":20,\"r\":8797,\"x\":16.3,\"y\":43.29},{\"t\":20,\"r\":9330,\"x\":16.16,\"y\":93.54},{\"t\":20,\"r\":8815,\"x\":-2.26,\"y\":94.97},{\"t\":20,\"r\":8810,\"x\":-22.24,\"y\":95.38},{\"t\":22,\"r\":8827,\"x\":-23.88,\"y\":102.61,\"s\":336},{\"t\":2,\"l\":[8824,9335,9331,8804,8808,8829,9333]},{\"t\":3,\"r\":8808,\"x\":25.84,\"y\":69.06,\"ms\":4908},{\"t\":21,\"s\":316},{\"t\":1,\"l\":[8827,9330,8815,8801,8808,8797,8804]},{\"t\":20,\"r\":8827,\"x\":16.09,\"y\":20.04},{\"t\":20,\"r\":8797,\"x\":1.97,\"y\":27.2},{\"t\":20,\"r\":8804,\"x\":-14.4,\"y\":31.56},{\"t\":20,\"r\":8801,\"x\":2.04,\"y\":54.54},{\"t\":20,\"r\":8808,\"x\":-23.88,\"y\":85.15},{\"t\":20,\"r\":8804,\"x\":-16.85,\"y\":82.02},{\"t\":22,\"r\":9330,\"x\":-5.39,\"y\":109.7,\"s\":288},{\"t\":2,\"l\":[8824,8808,8814,8828,9328,9332,8805]},{\"t\":3,\"r\":8808,\"x\":26.39,\"y\":60,\"ms\":8249},{\"t\":5,\"r\":8808},{\"t\":20,\"r\":8808,\"x\":26.12,\"y\":58.63},{\"t\":20,\"r\":8805,\"x\":10.98,\"y\":50.86},{\"t\":8,\"x\":-15.21,\"y\":51.54},{\"t\":5,\"r\":8828,\"h\":1},{\"t\":20,\"r\":8814,\"x\":-13.1,\"y\":20.86},{\"t\":42},{\"t\":41,\"l\":[8824,8808,8814,9328,9332,8805,8804]},{\"t\":20,\"r\":8814,\"x\":-13.1,\"y\":20.86},{\"t\":20,\"r\":8808,\"x\":-22.51,\"y\":38.11},{\"t\":20,\"r\":8814,\"x\":-6.96,\"y\":31.43},{\"t\":20,\"r\":9332,\"x\":12.54,\"y\":35.52},{\"t\":20,\"r\":8814,\"x\":-7.78,\"y\":39.27},{\"t\":20,\"r\":8808,\"x\":-14.33,\"y\":48.47},{\"t\":20,\"r\":8824,\"x\":5.31,\"y\":95.18},{\"t\":20,\"r\":9332,\"x\":-17.26,\"y\":96.13},{\"t\":22,\"r\":9328,\"x\":-8.12,\"y\":101.86,\"s\":217},{\"t\":2,\"l\":[8829,9335,9331,9328,9333,8804,8824]},{\"t\":4,\"r\":8824,\"x\":0,\"y\":80},{\"t\":21,\"s\":159},{\"t\":1,\"l\":[8810,8803,8827,9330,8815,8801,8797]},{\"t\":20,\"r\":8827,\"x\":-10.64,\"y\":27.34},{\"t\":20,\"r\":8797,\"x\":-1.1,\"y\":40.09},{\"t\":20,\"r\":8815,\"x\":-16.31,\"y\":49.7},{\"t\":8,\"x\":1.63,\"y\":73.15},{\"t\":11},{\"t\":5,\"r\":9330},{\"t\":20,\"r\":8797,\"x\":-13.92,\"y\":19.36},{\"t\":20,\"r\":8827,\"x\":3.27,\"y\":15.34},{\"t\":20,\"r\":8815,\"x\":18.95,\"y\":19.84},{\"t\":20,\"r\":8810,\"x\":21.27,\"y\":35.72},{\"t\":20,\"r\":8801,\"x\":2.38,\"y\":34.43},{\"t\":20,\"r\":8815,\"x\":-16.65,\"y\":41.59},{\"t\":20,\"r\":9330,\"x\":-22.03,\"y\":54.81},{\"t\":10},{\"t\":20,\"r\":8797,\"x\":-4.85,\"y\":30.54},{\"t\":20,\"r\":8827,\"x\":-9.14,\"y\":33.95},{\"t\":20,\"r\":8815,\"x\":-22.03,\"y\":44.52},{\"t\":20,\"r\":8803,\"x\":-5.46,\"y\":50.38},{\"t\":20,\"r\":8827,\"x\":-1.51,\"y\":41.59},{\"t\":20,\"r\":8810,\"x\":10.77,\"y\":54.68},{\"t\":20,\"r\":8797,\"x\":18.14,\"y\":59.59},{\"t\":20,\"r\":8801,\"x\":20.59,\"y\":66.68},{\"t\":20,\"r\":8803,\"x\":22.98,\"y\":77.04},{\"t\":20,\"r\":8797,\"x\":8.72,\"y\":66.81},{\"t\":20,\"r\":8803,\"x\":-7.3,\"y\":74.38},{\"t\":20,\"r\":9330,\"x\":2.11,\"y\":80.72},{\"t\":22,\"r\":8815,\"h\":1,\"x\":-15.76,\"y\":109.84,\"s\":21},{\"t\":2,\"l\":[8810,8824,8829,8828,9332,8814,9328]},{\"t\":3,\"r\":8814,\"x\":17.93,\"y\":92.59,\"ms\":6090},{\"t\":9},{\"t\":20,\"r\":8810,\"x\":17.66,\"y\":13.43},{\"t\":8,\"x\":10.5,\"y\":90.34},{\"t\":25},{\"t\":1,\"l\":[8810,8827,9330,8815,8808,8797,8804]},{\"t\":20,\"r\":8827,\"x\":11.93,\"y\":23.65},{\"t\":20,\"r\":8797,\"x\":2.31,\"y\":37.63},{\"t\":20,\"r\":8827,\"x\":1.15,\"y\":33.34},{\"t\":20,\"r\":8804,\"x\":-14.74,\"y\":41.31},{\"t\":20,\"r\":8808,\"x\":-19.65,\"y\":49.77},{\"t\":20,\"r\":8827,\"x\":-15.62,\"y\":41.25},{\"t\":20,\"r\":8808,\"x\":20.25,\"y\":44.93},{\"t\":20,\"r\":8804,\"x\":22.98,\"y\":54.2},{\"t\":20,\"r\":8815,\"x\":12.34,\"y\":70.84},{\"t\":20,\"r\":8810,\"x\":-12.62,\"y\":80.04},{\"t\":20,\"r\":8827,\"x\":-7.71,\"y\":76.56},{\"t\":20,\"r\":8797,\"x\":-1.91,\"y\":75.68},{\"t\":20,\"r\":8827,\"x\":-5.53,\"y\":70.7},{\"t\":20,\"r\":8797,\"x\":0,\"y\":71.45},{\"t\":22,\"r\":8815,\"h\":1,\"x\":23.32,\"y\":102.81,\"s\":653},{\"t\":2,\"l\":[9328,8824,8829,9332,8814,8828,8805]},{\"t\":3,\"r\":8814,\"x\":-25.31,\"y\":58.36,\"ms\":9016},{\"t\":9},{\"t\":20,\"r\":8814,\"x\":-25.31,\"y\":39.2},{\"t\":20,\"r\":9328,\"x\":-21.22,\"y\":33.75},{\"t\":20,\"r\":8814,\"x\":-11.05,\"y\":33.68},{\"t\":8,\"x\":19.64,\"y\":48.54},{\"t\":9},{\"t\":20,\"r\":8814,\"x\":-21.22,\"y\":59.11},{\"t\":8,\"x\":-20.19,\"y\":106.84},{\"t\":21,\"s\":549},{\"t\":1,\"l\":[8810,8827,9330,8815,9334,8801,8797]},{\"t\":20,\"r\":8797,\"x\":3.34,\"y\":32.31},{\"t\":20,\"r\":8827,\"x\":6.2,\"y\":42.88},{\"t\":42},{\"t\":41,\"l\":[8810,8827,9330,8815,9334,8801,8797]},{\"t\":20,\"r\":8827,\"x\":14.66,\"y\":30.75},{\"t\":20,\"r\":9334,\"x\":-7.92,\"y\":29.72},{\"t\":20,\"r\":8827,\"x\":-14.19,\"y\":14.52},{\"t\":20,\"r\":9334,\"x\":-3.89,\"y\":15.81},{\"t\":20,\"r\":8810,\"x\":14.25,\"y\":17.72},{\"t\":20,\"r\":8801,\"x\":-2.26,\"y\":24.47},{\"t\":20,\"r\":9330,\"x\":6.68,\"y\":29.72},{\"t\":20,\"r\":8810,\"x\":19.84,\"y\":39.54},{\"t\":20,\"r\":9334,\"x\":15.82,\"y\":50.72},{\"t\":22,\"r\":8801,\"h\":1,\"x\":-13.99,\"y\":105.4,\"s\":495},{\"t\":2,\"l\":[8824,8808,8804,9331,9335,9333,8829]},{\"t\":3,\"r\":8808,\"x\":-25.65,\"y\":74.93,\"ms\":7044},{\"t\":5,\"r\":9333},{\"t\":20,\"r\":8804,\"x\":-26.67,\"y\":59.31},{\"t\":20,\"r\":9335,\"x\":-19.72,\"y\":51.54},{\"t\":20,\"r\":8804,\"x\":-4.17,\"y\":50.79},{\"t\":20,\"r\":9333,\"x\":15.68,\"y\":57.54},{\"t\":20,\"r\":8808,\"x\":19.91,\"y\":69.95},{\"t\":20,\"r\":9333,\"x\":9.75,\"y\":64.5},{\"t\":20,\"r\":8808,\"x\":18,\"y\":60.34},{\"t\":14,\"s\":435},{\"t\":41,\"l\":[8810,8803,8827,8815,8808,8797,8804]},{\"t\":20,\"r\":8797,\"x\":18,\"y\":60.34},{\"t\":20,\"r\":8804,\"x\":5.04,\"y\":55.36},{\"t\":20,\"r\":8797,\"x\":14.25,\"y\":55.7},{\"t\":20,\"r\":8804,\"x\":-0.48,\"y\":45.68},{\"t\":20,\"r\":8797,\"x\":-1.1,\"y\":40.56},{\"t\":12},{\"t\":20,\"r\":8827,\"x\":16.3,\"y\":48.47},{\"t\":20,\"r\":8797,\"x\":20.66,\"y\":57.2},{\"t\":8,\"x\":-8.46,\"y\":93.2},{\"t\":9},{\"t\":20,\"r\":8808,\"x\":-25.72,\"y\":72.75},{\"t\":20,\"r\":8804,\"x\":-14.8,\"y\":75.88},{\"t\":20,\"r\":8797,\"x\":-25.03,\"y\":92.11},{\"t\":22,\"r\":8803,\"x\":-22.31,\"y\":109.29,\"s\":372},{\"t\":2,\"l\":[8828,9328,9333,8824,8814,9332,8805]},{\"t\":3,\"r\":8814,\"x\":-25.31,\"y\":60.06,\"ms\":9163},{\"t\":9},{\"t\":20,\"r\":9333,\"x\":-13.65,\"y\":20.11},{\"t\":20,\"r\":8814,\"x\":8.32,\"y\":10.29},{\"t\":20,\"r\":9328,\"x\":21.14,\"y\":20.59},{\"t\":12},{\"t\":20,\"r\":8814,\"x\":23.66,\"y\":49.5},{\"t\":20,\"r\":9328,\"x\":14.11,\"y\":45.06},{\"t\":20,\"r\":9332,\"x\":-17.53,\"y\":53.38},{\"t\":20,\"r\":8805,\"x\":-23.47,\"y\":66.75},{\"t\":20,\"r\":9333,\"x\":-9.89,\"y\":74.93},{\"t\":20,\"r\":8814,\"x\":-7.98,\"y\":81.4},{\"t\":22,\"r\":8828,\"x\":-17.4,\"y\":108.95,\"s\":307},{\"t\":2,\"l\":[8829,9335,8804,9333,9331,8824,8808]},{\"t\":3,\"r\":8808,\"x\":-26.47,\"y\":63.68,\"ms\":6627},{\"t\":5,\"r\":8804,\"h\":1},{\"t\":20,\"r\":8804,\"x\":9.95,\"y\":62.18},{\"t\":20,\"r\":8824,\"x\":18.2,\"y\":63.54},{\"t\":20,\"r\":9331,\"x\":2.65,\"y\":89.79},{\"t\":22,\"r\":8804,\"x\":18.95,\"y\":102.81,\"s\":278},{\"t\":2,\"l\":[8824,8828,8814,9328,8805,9332,9333]},{\"t\":3,\"r\":8814,\"x\":-24.42,\"y\":54.68,\"ms\":11250},{\"t\":5,\"r\":9332},{\"t\":20,\"r\":8814,\"x\":-9.01,\"y\":64.56},{\"t\":20,\"r\":9333,\"x\":-19.51,\"y\":72.06},{\"t\":8,\"x\":-8.6,\"y\":71.04},{\"t\":11},{\"t\":9},{\"t\":20,\"r\":8814,\"x\":-25.38,\"y\":20.25},{\"t\":14,\"s\":175},{\"t\":41,\"l\":[8810,8803,8827,8815,8808,8797,8804]},{\"t\":20,\"r\":8797,\"x\":-25.38,\"y\":20.25},{\"t\":20,\"r\":8804,\"x\":-14.8,\"y\":9.54},{\"t\":20,\"r\":8797,\"x\":-12.35,\"y\":15.95},{\"t\":20,\"r\":8808,\"x\":11.32,\"y\":39.75},{\"t\":20,\"r\":8804,\"x\":13.77,\"y\":30.06},{\"t\":20,\"r\":8797,\"x\":15.41,\"y\":35.65},{\"t\":20,\"r\":8804,\"x\":13.57,\"y\":30.27},{\"t\":20,\"r\":8797,\"x\":12.54,\"y\":35.93},{\"t\":20,\"r\":8815,\"x\":4.91,\"y\":36},{\"t\":20,\"r\":8827,\"x\":-5.94,\"y\":25.22},{\"t\":20,\"r\":8797,\"x\":3,\"y\":34.84},{\"t\":20,\"r\":8810,\"x\":21.82,\"y\":38.59},{\"t\":20,\"r\":8827,\"x\":24.07,\"y\":32.52},{\"t\":20,\"r\":8810,\"x\":18.34,\"y\":30.4},{\"t\":20,\"r\":8827,\"x\":7.63,\"y\":25.63},{\"t\":20,\"r\":8804,\"x\":-13.3,\"y\":20.45},{\"t\":20,\"r\":8815,\"x\":-19.31,\"y\":31.5},{\"t\":12},{\"t\":20,\"r\":8827,\"x\":-14.05,\"y\":26.45},{\"t\":10},{\"t\":20,\"r\":8797,\"x\":-18.15,\"y\":10.5},{\"t\":20,\"r\":8815,\"x\":-6.35,\"y\":27.06},{\"t\":20,\"r\":8827,\"x\":-12.62,\"y\":37.56},{\"t\":20,\"r\":8808,\"x\":-5.94,\"y\":39.81},{\"t\":20,\"r\":8797,\"x\":-23.67,\"y\":51.68},{\"t\":20,\"r\":8808,\"x\":-18.42,\"y\":56.25},{\"t\":20,\"r\":8797,\"x\":-15.49,\"y\":39.13},{\"t\":20,\"r\":8827,\"x\":-6.01,\"y\":46.7},{\"t\":20,\"r\":8808,\"x\":-5.6,\"y\":64.97},{\"t\":20,\"r\":8804,\"x\":13.02,\"y\":54.4},{\"t\":20,\"r\":8808,\"x\":-11.53,\"y\":55.09},{\"t\":20,\"r\":8797,\"x\":0.4,\"y\":59.86},{\"t\":20,\"r\":8827,\"x\":20.73,\"y\":81.2},{\"t\":22,\"r\":8815,\"x\":-17.26,\"y\":103.7,\"s\":23},{\"t\":2,\"l\":[9328,8814,8828,8829,8824,8810,9332]},{\"t\":3,\"r\":8814,\"x\":-0.62,\"y\":100.36,\"ms\":6234},{\"t\":5,\"r\":8810},{\"t\":20,\"r\":8810,\"x\":17.66,\"y\":24.54},{\"t\":20,\"r\":9332,\"x\":-10.44,\"y\":24.68},{\"t\":20,\"r\":8814,\"x\":-21.97,\"y\":32.72},{\"t\":26}]","updateMoment":"2021-08-15T01:25:54.649Z","blocks":10,"completionsNumer":296,"completionsDenom":314,"dLineBreaksNumer":7,"dLineBreaksDenom":17,"hucksNumer":5,"hucksDenom":10,"oLineHoldsNumer":13,"oLineHoldsDenom":22,"redZoneNumer":15,"redZoneDenom":18,"turnovers":18,"team_season_id":214},"rostersAway":[{"id":9687,"team_season_id":215,"player_id":25,"jersey_number":"43","active":false,"player":{"id":25,"first_name":"Adnan","last_name":"Raslan","ext_player_id":"araslan"}},{"id":9323,"team_season_id":215,"player_id":139,"jersey_number":"80","active":true,"player":{"id":139,"first_name":"Antoine","last_name":"Davis","ext_player_id":"adavis2"}},{"id":9237,"team_season_id":215,"player_id":156,"jersey_number":"2","active":true,"player":{"id":156,"first_name":"Austin","last_name":"Taylor","ext_player_id":"ataylor"}},{"id":9250,"team_season_id":215,"player_id":359,"jersey_number":"8","active":true,"player":{"id":359,"first_name":"Christian","last_name":"Olsen","ext_player_id":"colsen"}},{"id":9238,"team_season_id":215,"player_id":468,"jersey_number":"00","active":true,"player":{"id":468,"first_name":"Daniel","last_name":"Sperling","ext_player_id":"dsperling"}},{"id":9588,"team_season_id":215,"player_id":565,"jersey_number":"99","active":false,"player":{"id":565,"first_name":"Dylan","last_name":"Tunnell","ext_player_id":"dtunnell"}},{"id":9712,"team_season_id":215,"player_id":761,"jersey_number":"21","active":false,"player":{"id":761,"first_name":"Jacques","last_name":"Perivier","ext_player_id":"jperivier"}},{"id":9252,"team_season_id":215,"player_id":778,"jersey_number":"14","active":true,"player":{"id":778,"first_name":"Jakeem","last_name":"Polk","ext_player_id":"jpolk"}},{"id":9248,"team_season_id":215,"player_id":814,"jersey_number":"9","active":true,"player":{"id":814,"first_name":"Javier","last_name":"Ortiz","ext_player_id":"jortiz"}},{"id":9270,"team_season_id":215,"player_id":923,"jersey_number":"42","active":true,"player":{"id":923,"first_name":"Jon","last_name":"Fey","ext_player_id":"jfey"}},{"id":9244,"team_season_id":215,"player_id":984,"jersey_number":"34","active":true,"player":{"id":984,"first_name":"Josh","last_name":"Turner","ext_player_id":"jturner"}},{"id":9240,"team_season_id":215,"player_id":990,"jersey_number":"81","active":true,"player":{"id":990,"first_name":"JP","last_name":"Burns","ext_player_id":"jburns"}},{"id":9245,"team_season_id":215,"player_id":1023,"jersey_number":"11","active":true,"player":{"id":1023,"first_name":"Kelvin","last_name":"Williams","ext_player_id":"kwilliams"}},{"id":9325,"team_season_id":215,"player_id":1145,"jersey_number":"99","active":true,"player":{"id":1145,"first_name":"Mac","last_name":"McClellan","ext_player_id":"mmcclella"}},{"id":9241,"team_season_id":215,"player_id":1218,"jersey_number":"12","active":true,"player":{"id":1218,"first_name":"Matt","last_name":"Smith","ext_player_id":"msmith"}},{"id":9587,"team_season_id":215,"player_id":1240,"jersey_number":"","active":false,"player":{"id":1240,"first_name":"Matthew","last_name":"Knowles","ext_player_id":"mknowles"}},{"id":9247,"team_season_id":215,"player_id":1276,"jersey_number":"5","active":true,"player":{"id":1276,"first_name":"Michael","last_name":"Fairley","ext_player_id":"mfairley"}},{"id":9262,"team_season_id":215,"player_id":1414,"jersey_number":"7","active":true,"player":{"id":1414,"first_name":"Parker","last_name":"Bray","ext_player_id":"pbray"}},{"id":9246,"team_season_id":215,"player_id":1469,"jersey_number":"4","active":true,"player":{"id":1469,"first_name":"Player","last_name":"Pierce","ext_player_id":"ppierce"}},{"id":9713,"team_season_id":215,"player_id":1571,"jersey_number":"96","active":false,"player":{"id":1571,"first_name":"Sam","last_name":"Gainer","ext_player_id":"sgainer"}},{"id":9264,"team_season_id":215,"player_id":1685,"jersey_number":"23","active":true,"player":{"id":1685,"first_name":"Sun","last_name":"Choi","ext_player_id":"schoi"}},{"id":9265,"team_season_id":215,"player_id":1762,"jersey_number":"87","active":true,"player":{"id":1762,"first_name":"Trenton","last_name":"Spinks","ext_player_id":"tspinks"}},{"id":9251,"team_season_id":215,"player_id":1782,"jersey_number":"10","active":true,"player":{"id":1782,"first_name":"Tyler","last_name":"Kunsa","ext_player_id":"tkunsa"}},{"id":9322,"team_season_id":215,"player_id":1880,"jersey_number":"33","active":true,"player":{"id":1880,"first_name":"Devon","last_name":"Rogers","ext_player_id":"drogers"}},{"id":9324,"team_season_id":215,"player_id":1885,"jersey_number":"82","active":true,"player":{"id":1885,"first_name":"Sam","last_name":"Batson","ext_player_id":"sbatson"}},{"id":9327,"team_season_id":215,"player_id":1886,"jersey_number":"49","active":true,"player":{"id":1886,"first_name":"Tyler","last_name":"French","ext_player_id":"tfrench"}},{"id":9253,"team_season_id":215,"player_id":1887,"jersey_number":"1","active":true,"player":{"id":1887,"first_name":"Will","last_name":"Lindquist","ext_player_id":"wlindquis"}},{"id":9714,"team_season_id":215,"player_id":2063,"jersey_number":"95","active":false,"player":{"id":2063,"first_name":"Chris","last_name":"Calhoun","ext_player_id":"ccalhoun"}},{"id":9259,"team_season_id":215,"player_id":2127,"jersey_number":"32","active":true,"player":{"id":2127,"first_name":"Karl","last_name":"Ekwurtzel","ext_player_id":"kekwurtze"}},{"id":9242,"team_season_id":215,"player_id":2064,"jersey_number":"55","active":true,"player":{"id":2064,"first_name":"Elijah","last_name":"Jaime","ext_player_id":"ejaime"}},{"id":9256,"team_season_id":215,"player_id":2238,"jersey_number":"6","active":true,"player":{"id":2238,"first_name":"Brett","last_name":"Hulsmeyer","ext_player_id":"bhulsmeye"}},{"id":9243,"team_season_id":215,"player_id":2239,"jersey_number":"17","active":true,"player":{"id":2239,"first_name":"Hayden","last_name":"Austin-Knab","ext_player_id":"haustinkn"}},{"id":9718,"team_season_id":215,"player_id":2345,"jersey_number":"20","active":false,"player":{"id":2345,"first_name":"John","last_name":"Boezi","ext_player_id":"jboezi"}},{"id":9254,"team_season_id":215,"player_id":2346,"jersey_number":"26","active":true,"player":{"id":2346,"first_name":"Christian","last_name":"Gaeta","ext_player_id":"cgaeta"}},{"id":9255,"team_season_id":215,"player_id":2370,"jersey_number":"36","active":true,"player":{"id":2370,"first_name":"Will","last_name":"Frolich","ext_player_id":"wfrolich"}},{"id":9320,"team_season_id":215,"player_id":2530,"jersey_number":"18","active":true,"player":{"id":2530,"first_name":"Adam","last_name":"Miller","ext_player_id":"amiller1"}},{"id":9257,"team_season_id":215,"player_id":2531,"jersey_number":"22","active":true,"player":{"id":2531,"first_name":"Tanner","last_name":"Robinson","ext_player_id":"trobinson"}},{"id":9258,"team_season_id":215,"player_id":2532,"jersey_number":"37","active":true,"player":{"id":2532,"first_name":"Madison","last_name":"Head","ext_player_id":"mhead"}},{"id":9263,"team_season_id":215,"player_id":2533,"jersey_number":"62","active":true,"player":{"id":2533,"first_name":"Sam","last_name":"Diffin","ext_player_id":"sdiffin"}},{"id":9267,"team_season_id":215,"player_id":2534,"jersey_number":"25","active":true,"player":{"id":2534,"first_name":"James","last_name":"Russnogle","ext_player_id":"jrussnogl"}},{"id":9321,"team_season_id":215,"player_id":2535,"jersey_number":"32","active":true,"player":{"id":2535,"first_name":"David","last_name":"Perry","ext_player_id":"dperry"}},{"id":9269,"team_season_id":215,"player_id":2536,"jersey_number":"44","active":true,"player":{"id":2536,"first_name":"Fletcher","last_name":"Hare","ext_player_id":"fhare"}},{"id":9271,"team_season_id":215,"player_id":2537,"jersey_number":"47","active":true,"player":{"id":2537,"first_name":"Ben","last_name":"Gagne-Maynard","ext_player_id":"bgagnemay"}},{"id":9272,"team_season_id":215,"player_id":2538,"jersey_number":"27","active":true,"player":{"id":2538,"first_name":"Jeffrey","last_name":"Oravic","ext_player_id":"joravic"}},{"id":9273,"team_season_id":215,"player_id":2539,"jersey_number":"24","active":true,"player":{"id":2539,"first_name":"Zachary","last_name":"Cole","ext_player_id":"zcole"}},{"id":9318,"team_season_id":215,"player_id":2562,"jersey_number":"9","active":true,"player":{"id":2562,"first_name":"Kennith","last_name":"Taylor","ext_player_id":"ktaylor"}},{"id":9568,"team_season_id":215,"player_id":2679,"jersey_number":"19","active":true,"player":{"id":2679,"first_name":"John","last_name":"Stubbs","ext_player_id":"jstubbs"}},{"id":9615,"team_season_id":215,"player_id":2713,"jersey_number":"36","active":false,"player":{"id":2713,"first_name":"Dean","last_name":"Ramsey","ext_player_id":"dramsey"}}],"tsgAway":{"id":88,"teamSeasonId":215,"gameId":2719,"rosterIds":[9273,9259,9247,9262,9271,9256,9242,9587,9251,9615,9257,9265,9237,9568,9318,9245,9252,9250,9323,9240],"valid":true,"startOnOffense":true,"events":"[{\"t\":1,\"l\":[9262,9237,9257,9323,9251,9568,9259]},{\"t\":20,\"r\":9251,\"x\":8.23,\"y\":31.45},{\"t\":20,\"r\":9237,\"x\":-0.22,\"y\":49.22},{\"t\":20,\"r\":9568,\"x\":-0.44,\"y\":63.27},{\"t\":20,\"r\":9259,\"x\":-19.46,\"y\":99.1},{\"t\":20,\"r\":9237,\"x\":-21.21,\"y\":93.13},{\"t\":12,\"c\":true},{\"t\":22,\"r\":9257,\"x\":2.69,\"y\":116.79,\"s\":682},{\"t\":2,\"l\":[9318,9273,9250,9265,9256,9252,9240]},{\"t\":3,\"r\":9252,\"x\":7.94,\"y\":87.45,\"ms\":5391},{\"t\":9},{\"t\":20,\"r\":9240,\"x\":-9.55,\"y\":20.46},{\"t\":20,\"r\":9250,\"x\":3.78,\"y\":18.85},{\"t\":20,\"r\":9240,\"x\":-11.15,\"y\":27.88},{\"t\":20,\"r\":9256,\"x\":-17.93,\"y\":31.38},{\"t\":20,\"r\":9252,\"x\":-0.08,\"y\":37.5},{\"t\":20,\"r\":9256,\"x\":-0.59,\"y\":45.94},{\"t\":20,\"r\":9250,\"x\":-7.22,\"y\":41.86},{\"t\":20,\"r\":9256,\"x\":0.51,\"y\":45.21},{\"t\":20,\"r\":9250,\"x\":6.99,\"y\":51.69},{\"t\":20,\"r\":9252,\"x\":20.47,\"y\":67.2},{\"t\":22,\"r\":9240,\"x\":16.39,\"y\":109.15,\"s\":605},{\"t\":2,\"l\":[9587,9256,9271,9265,9247,9615,9245]},{\"t\":3,\"r\":9615,\"x\":2.47,\"y\":96.33,\"ms\":5916},{\"t\":11},{\"t\":21,\"s\":502},{\"t\":1,\"l\":[9237,9259,9242,9251,9323,9262,9568]},{\"t\":20,\"r\":9251,\"x\":11.22,\"y\":23.59},{\"t\":20,\"r\":9237,\"x\":5.17,\"y\":31.01},{\"t\":20,\"r\":9251,\"x\":18.28,\"y\":39.24},{\"t\":20,\"r\":9568,\"x\":18.79,\"y\":52.28},{\"t\":19,\"r\":9323,\"x\":17.26,\"y\":65.75},{\"t\":9},{\"t\":20,\"r\":9237,\"x\":26.52,\"y\":25.33},{\"t\":20,\"r\":9568,\"x\":6.99,\"y\":22.13},{\"t\":20,\"r\":9251,\"x\":-3.58,\"y\":29.49},{\"t\":20,\"r\":9259,\"x\":-12.54,\"y\":43.03},{\"t\":20,\"r\":9262,\"x\":-3.43,\"y\":40.26},{\"t\":20,\"r\":9237,\"x\":7.57,\"y\":51.99},{\"t\":10},{\"t\":20,\"r\":9568,\"x\":19.01,\"y\":62.91},{\"t\":20,\"r\":9242,\"x\":3.06,\"y\":92.76},{\"t\":20,\"r\":9262,\"x\":-1.9,\"y\":86.79},{\"t\":22,\"r\":9259,\"x\":-11.08,\"y\":105.72,\"s\":371},{\"t\":2,\"l\":[9273,9265,9318,9250,9245,9240,9252]},{\"t\":3,\"r\":9252,\"x\":6.48,\"y\":95.97,\"ms\":6508},{\"t\":21,\"s\":327},{\"t\":1,\"l\":[9251,9257,9242,9262,9568,9237,9323]},{\"t\":20,\"r\":9251,\"x\":17.99,\"y\":20.24},{\"t\":20,\"r\":9237,\"x\":0.51,\"y\":25.04},{\"t\":20,\"r\":9262,\"x\":-11.81,\"y\":36.26},{\"t\":20,\"r\":9251,\"x\":12.24,\"y\":43.9},{\"t\":20,\"r\":9257,\"x\":13.98,\"y\":61.52},{\"t\":20,\"r\":9237,\"x\":16.75,\"y\":73.98},{\"t\":20,\"r\":9323,\"x\":18.65,\"y\":85.33},{\"t\":8,\"x\":20.03,\"y\":100.77},{\"t\":9},{\"t\":20,\"r\":9237,\"x\":8.74,\"y\":82.42},{\"t\":20,\"r\":9568,\"x\":0.43,\"y\":76.16},{\"t\":20,\"r\":9262,\"x\":10.71,\"y\":71.79},{\"t\":22,\"r\":9568,\"x\":18.21,\"y\":103.61,\"s\":254},{\"t\":2,\"l\":[9256,9271,9615,9250,9245,9587,9247]},{\"t\":3,\"r\":9615,\"x\":-0.37,\"y\":101.06,\"ms\":6569},{\"t\":11},{\"t\":5,\"r\":9247},{\"t\":20,\"r\":9250,\"x\":-6.78,\"y\":45},{\"t\":20,\"r\":9256,\"x\":1.09,\"y\":41.06},{\"t\":20,\"r\":9250,\"x\":7.72,\"y\":43.25},{\"t\":20,\"r\":9256,\"x\":-3.5,\"y\":44.92},{\"t\":20,\"r\":9250,\"x\":7.72,\"y\":46.45},{\"t\":20,\"r\":9256,\"x\":15.66,\"y\":54.1},{\"t\":20,\"r\":9271,\"x\":17.41,\"y\":67.71},{\"t\":20,\"r\":9247,\"x\":17.34,\"y\":60.29},{\"t\":22,\"r\":9256,\"x\":-1.1,\"y\":113.81,\"s\":167},{\"t\":2,\"l\":[9273,9318,9245,9240,9265,9252,9250]},{\"t\":3,\"r\":9252,\"x\":14.49,\"y\":88.76,\"ms\":7721},{\"t\":21,\"s\":119},{\"t\":1,\"l\":[9237,9251,9259,9257,9262,9242,9323]},{\"t\":20,\"r\":9251,\"x\":17.48,\"y\":22.28},{\"t\":20,\"r\":9237,\"x\":0.36,\"y\":29.34},{\"t\":20,\"r\":9251,\"x\":17.19,\"y\":34.73},{\"t\":20,\"r\":9257,\"x\":-2.48,\"y\":34.07},{\"t\":20,\"r\":9262,\"x\":-12.54,\"y\":46.82},{\"t\":20,\"r\":9259,\"x\":-15.16,\"y\":65.24},{\"t\":20,\"r\":9323,\"x\":1.6,\"y\":70.84},{\"t\":20,\"r\":9237,\"x\":6.84,\"y\":67.86},{\"t\":20,\"r\":9259,\"x\":16.68,\"y\":74.12},{\"t\":20,\"r\":9323,\"x\":9.1,\"y\":82.93},{\"t\":22,\"r\":9262,\"x\":3.49,\"y\":115.33,\"s\":66},{\"t\":2,\"l\":[9587,9615,9256,9271,9245,9252,9247]},{\"t\":3,\"r\":9615,\"x\":-1.68,\"y\":103.32,\"ms\":6338},{\"t\":21,\"s\":29},{\"t\":1,\"l\":[9237,9568,9262,9323,9259,9257,9242]},{\"t\":20,\"r\":9237,\"x\":0,\"y\":40},{\"t\":20,\"r\":9257,\"x\":-14.65,\"y\":46.09},{\"t\":8,\"x\":-0.81,\"y\":57.66},{\"t\":15,\"s\":13},{\"t\":40,\"l\":[9247,9252,9256,9245,9271,9615,9587]},{\"t\":21,\"s\":6},{\"t\":1,\"l\":[9265,9323,9262,9237,9615,9256,9252]},{\"t\":20,\"r\":9262,\"x\":13.47,\"y\":21.4},{\"t\":20,\"r\":9237,\"x\":-0.59,\"y\":27.45},{\"t\":20,\"r\":9262,\"x\":11.94,\"y\":33.85},{\"t\":23},{\"t\":2,\"l\":[9318,9252,9256,9240,9265,9250,9273]},{\"t\":3,\"r\":9252,\"x\":-7.22,\"y\":97.06,\"ms\":7764},{\"t\":5,\"r\":9256},{\"t\":20,\"r\":9256,\"x\":0.58,\"y\":48.34},{\"t\":20,\"r\":9250,\"x\":12.82,\"y\":50.24},{\"t\":20,\"r\":9240,\"x\":15.15,\"y\":61.52},{\"t\":20,\"r\":9256,\"x\":19.89,\"y\":70.77},{\"t\":20,\"r\":9250,\"x\":15,\"y\":59.41},{\"t\":14,\"s\":670},{\"t\":41,\"l\":[9237,9262,9251,9242,9259,9323,9568]},{\"t\":20,\"r\":9237,\"x\":15,\"y\":59.41},{\"t\":20,\"r\":9323,\"x\":18.79,\"y\":74.27},{\"t\":20,\"r\":9237,\"x\":6.26,\"y\":72.16},{\"t\":20,\"r\":9568,\"x\":14.93,\"y\":76.23},{\"t\":20,\"r\":9242,\"x\":23.24,\"y\":80.97},{\"t\":22,\"r\":9568,\"x\":24.62,\"y\":101.21,\"s\":650},{\"t\":2,\"l\":[9245,9615,9256,9247,9271,9587,9250]},{\"t\":3,\"r\":9256,\"x\":25.64,\"y\":39.24,\"ms\":1917},{\"t\":9},{\"t\":20,\"r\":9247,\"x\":4.22,\"y\":24.75},{\"t\":20,\"r\":9256,\"x\":-4.38,\"y\":32.54},{\"t\":20,\"r\":9247,\"x\":5.82,\"y\":34.22},{\"t\":20,\"r\":9256,\"x\":12.53,\"y\":38.81},{\"t\":20,\"r\":9615,\"x\":13.69,\"y\":50.97},{\"t\":14,\"s\":577},{\"t\":41,\"l\":[9259,9237,9242,9262,9323,9568,9257]},{\"t\":20,\"r\":9262,\"x\":13.69,\"y\":50.97},{\"t\":20,\"r\":9323,\"x\":7.06,\"y\":65.02},{\"t\":20,\"r\":9568,\"x\":14.64,\"y\":72.66},{\"t\":20,\"r\":9323,\"x\":13.55,\"y\":90.94},{\"t\":12,\"c\":true},{\"t\":22,\"r\":9259,\"x\":13.91,\"y\":104.19,\"s\":542},{\"t\":2,\"l\":[9273,9252,9240,9250,9318,9265,9256]},{\"t\":3,\"r\":9252,\"x\":-4.6,\"y\":95.97,\"ms\":7128},{\"t\":11},{\"t\":5,\"r\":9250},{\"t\":20,\"r\":9250,\"x\":-10.35,\"y\":59.56},{\"t\":20,\"r\":9256,\"x\":-15.31,\"y\":69.53},{\"t\":20,\"r\":9250,\"x\":-9.04,\"y\":60.07},{\"t\":20,\"r\":9256,\"x\":-1.54,\"y\":64.8},{\"t\":20,\"r\":9252,\"x\":8.88,\"y\":73.25},{\"t\":20,\"r\":9256,\"x\":-0.81,\"y\":66.11},{\"t\":20,\"r\":9318,\"x\":14.42,\"y\":80.09},{\"t\":22,\"r\":9273,\"x\":22.65,\"y\":107.98,\"s\":444},{\"t\":2,\"l\":[9256,9271,9615,9245,9247,9587,9262]},{\"t\":3,\"r\":9615,\"x\":-9.48,\"y\":91.6,\"ms\":6824},{\"t\":5,\"r\":9256},{\"t\":20,\"r\":9256,\"x\":-10.21,\"y\":38.22},{\"t\":20,\"r\":9615,\"x\":3.06,\"y\":42.08},{\"t\":20,\"r\":9271,\"x\":12.02,\"y\":47.69},{\"t\":20,\"r\":9247,\"x\":-0.88,\"y\":50.09},{\"t\":10},{\"t\":20,\"r\":9615,\"x\":13.77,\"y\":60.21},{\"t\":20,\"r\":9256,\"x\":15.3,\"y\":70.41},{\"t\":20,\"r\":9247,\"x\":0.21,\"y\":65.24},{\"t\":20,\"r\":9256,\"x\":6.55,\"y\":58.17},{\"t\":20,\"r\":9262,\"x\":-3.07,\"y\":55.04},{\"t\":8,\"x\":8.59,\"y\":105.21},{\"t\":43},{\"t\":40,\"l\":[9256,9271,9245,9247,9587,9262,9252]},{\"t\":11},{\"t\":21,\"s\":264},{\"t\":1,\"l\":[9237,9323,9257,9242,9568,9259,9251]},{\"t\":20,\"r\":9257,\"x\":-7.07,\"y\":28.76},{\"t\":20,\"r\":9237,\"x\":5.1,\"y\":38.22},{\"t\":19,\"r\":9568,\"x\":14.42,\"y\":54.24},{\"t\":9},{\"t\":20,\"r\":9237,\"x\":22.14,\"y\":20.82},{\"t\":20,\"r\":9257,\"x\":15.51,\"y\":40.92},{\"t\":20,\"r\":9237,\"x\":1.31,\"y\":38.15},{\"t\":20,\"r\":9568,\"x\":0.58,\"y\":49.22},{\"t\":20,\"r\":9242,\"x\":5.9,\"y\":59.92},{\"t\":20,\"r\":9237,\"x\":1.82,\"y\":60.8},{\"t\":22,\"r\":9259,\"x\":2.91,\"y\":113.51,\"s\":177},{\"t\":2,\"l\":[9265,9247,9273,9240,9318,9250,9252]},{\"t\":3,\"r\":9252,\"x\":-10.35,\"y\":95.16,\"ms\":7578},{\"t\":21,\"s\":146},{\"t\":1,\"l\":[9323,9318,9257,9242,9568,9262,9237]},{\"t\":20,\"r\":9237,\"x\":25.93,\"y\":64},{\"t\":12},{\"t\":20,\"r\":9262,\"x\":19.23,\"y\":76.52},{\"t\":12},{\"t\":20,\"r\":9568,\"x\":5.31,\"y\":72.88},{\"t\":20,\"r\":9318,\"x\":17.92,\"y\":81.62},{\"t\":20,\"r\":9237,\"x\":20.76,\"y\":86.65},{\"t\":22,\"r\":9323,\"x\":-2.41,\"y\":104.7,\"s\":80},{\"t\":2,\"l\":[9265,9256,9247,9615,9245,9587,9271]},{\"t\":3,\"r\":9615,\"x\":-9.84,\"y\":107.33,\"ms\":7798},{\"t\":21,\"s\":21},{\"t\":1,\"l\":[9259,9323,9251,9568,9237,9242,9257]},{\"t\":20,\"r\":9257,\"x\":-12.17,\"y\":25.26},{\"t\":20,\"r\":9237,\"x\":1.89,\"y\":29.7},{\"t\":19,\"r\":9257,\"x\":-10.35,\"y\":31.67},{\"t\":21,\"s\":8},{\"t\":1,\"l\":[9237,9256,9615,9262,9242,9323,9252]},{\"t\":20,\"r\":9262,\"x\":-16.11,\"y\":17.76},{\"t\":20,\"r\":9615,\"x\":-15.82,\"y\":39.9},{\"t\":22,\"r\":9242,\"x\":-0.3,\"y\":109,\"s\":0},{\"t\":24},{\"t\":1,\"l\":[9237,9251,9323,9259,9568,9262,9257]},{\"t\":20,\"r\":9251,\"x\":7.86,\"y\":23.66},{\"t\":20,\"r\":9237,\"x\":0.07,\"y\":35.46},{\"t\":20,\"r\":9323,\"x\":5.31,\"y\":53.15},{\"t\":20,\"r\":9251,\"x\":13.77,\"y\":57.45},{\"t\":20,\"r\":9237,\"x\":13.69,\"y\":69.83},{\"t\":22,\"r\":9259,\"x\":-20.55,\"y\":108.85,\"s\":692},{\"t\":2,\"l\":[9265,9240,9273,9250,9318,9252,9256]},{\"t\":3,\"r\":9252,\"x\":15.44,\"y\":91.23,\"ms\":7405},{\"t\":21,\"s\":643},{\"t\":1,\"l\":[9323,9262,9237,9257,9259,9251,9242]},{\"t\":20,\"r\":9251,\"x\":-0.22,\"y\":35.97},{\"t\":20,\"r\":9237,\"x\":6.55,\"y\":41.65},{\"t\":20,\"r\":9323,\"x\":15.3,\"y\":48.85},{\"t\":20,\"r\":9237,\"x\":4.51,\"y\":46.74},{\"t\":20,\"r\":9257,\"x\":0,\"y\":55.33},{\"t\":20,\"r\":9259,\"x\":-4.74,\"y\":70.77},{\"t\":20,\"r\":9257,\"x\":-4.01,\"y\":62.69},{\"t\":20,\"r\":9237,\"x\":-17.42,\"y\":65.6},{\"t\":20,\"r\":9257,\"x\":-23.61,\"y\":98.15},{\"t\":22,\"r\":9262,\"x\":-23.76,\"y\":113.37,\"s\":598},{\"t\":2,\"l\":[9587,9247,9615,9568,9271,9245,9256]},{\"t\":3,\"r\":9615,\"x\":10.78,\"y\":93.85,\"ms\":6529},{\"t\":5,\"r\":9256},{\"t\":20,\"r\":9247,\"x\":23.09,\"y\":19.51},{\"t\":20,\"r\":9256,\"x\":8.01,\"y\":17.98},{\"t\":20,\"r\":9247,\"x\":22,\"y\":21.33},{\"t\":20,\"r\":9568,\"x\":6.26,\"y\":18.56},{\"t\":20,\"r\":9271,\"x\":13.55,\"y\":44.19},{\"t\":20,\"r\":9256,\"x\":0.21,\"y\":49.8},{\"t\":14,\"s\":509},{\"t\":41,\"l\":[9256,9323,9262,9568,9242,9259,9237]},{\"t\":20,\"r\":9237,\"x\":0.43,\"y\":35.46},{\"t\":20,\"r\":9256,\"x\":-9.7,\"y\":44.19},{\"t\":20,\"r\":9323,\"x\":-18.37,\"y\":54.1},{\"t\":20,\"r\":9259,\"x\":2.47,\"y\":99.39},{\"t\":12,\"c\":true},{\"t\":20,\"r\":9262,\"x\":-3.87,\"y\":93.05},{\"t\":20,\"r\":9568,\"x\":-4.67,\"y\":84.9},{\"t\":22,\"r\":9242,\"x\":-11.66,\"y\":102.59,\"s\":439},{\"t\":2,\"l\":[9240,9273,9252,9245,9250,9318,9265]},{\"t\":3,\"r\":9252,\"x\":-4.52,\"y\":96.69,\"ms\":6857},{\"t\":9},{\"t\":20,\"r\":9250,\"x\":6.19,\"y\":20.02},{\"t\":20,\"r\":9318,\"x\":3.78,\"y\":30.94},{\"t\":20,\"r\":9265,\"x\":6.7,\"y\":38.44},{\"t\":20,\"r\":9250,\"x\":-0.59,\"y\":37.42},{\"t\":20,\"r\":9245,\"x\":-8.75,\"y\":41.5},{\"t\":20,\"r\":9240,\"x\":1.16,\"y\":48.85},{\"t\":20,\"r\":9245,\"x\":0.14,\"y\":54.9},{\"t\":20,\"r\":9240,\"x\":-8.6,\"y\":58.83},{\"t\":20,\"r\":9252,\"x\":-14.43,\"y\":78.27},{\"t\":17},{\"t\":21,\"s\":336},{\"t\":1,\"l\":[9259,9242,9262,9257,9568,9237,9251]},{\"t\":20,\"r\":9237,\"x\":-26.02,\"y\":49.44},{\"t\":20,\"r\":9257,\"x\":-18.37,\"y\":37.42},{\"t\":20,\"r\":9568,\"x\":-3.28,\"y\":47.98},{\"t\":22,\"r\":9262,\"x\":2.4,\"y\":108.78,\"s\":316},{\"t\":2,\"l\":[9245,9587,9271,9323,9256,9615,9247]},{\"t\":3,\"r\":9615,\"x\":-16.62,\"y\":98.81,\"ms\":5706},{\"t\":21,\"s\":288},{\"t\":1,\"l\":[9242,9237,9262,9257,9251,9568,9323]},{\"t\":20,\"r\":9237,\"x\":-25.94,\"y\":59.41},{\"t\":20,\"r\":9262,\"x\":-12.32,\"y\":59.78},{\"t\":8,\"x\":-12.32,\"y\":69.75},{\"t\":5,\"r\":9323},{\"t\":20,\"r\":9323,\"x\":3.06,\"y\":71.28},{\"t\":20,\"r\":9237,\"x\":-1.97,\"y\":65.31},{\"t\":20,\"r\":9262,\"x\":-13.19,\"y\":72.81},{\"t\":8,\"x\":19.01,\"y\":98.44},{\"t\":43},{\"t\":40,\"l\":[9242,9237,9262,9257,9568,9323,9256]},{\"t\":21,\"s\":217},{\"t\":1,\"l\":[9568,9257,9323,9237,9259,9250,9251]},{\"t\":20,\"r\":9237,\"x\":-1.1,\"y\":76.09},{\"t\":20,\"r\":9251,\"x\":10.05,\"y\":76.45},{\"t\":20,\"r\":9237,\"x\":1.82,\"y\":72.59},{\"t\":20,\"r\":9250,\"x\":-3.5,\"y\":79.73},{\"t\":20,\"r\":9251,\"x\":-6.34,\"y\":74.49},{\"t\":20,\"r\":9237,\"x\":8.37,\"y\":80.09},{\"t\":20,\"r\":9323,\"x\":13.33,\"y\":93.34},{\"t\":22,\"r\":9250,\"x\":9.32,\"y\":106.01,\"s\":159},{\"t\":2,\"l\":[9318,9250,9245,9265,9273,9252,9240]},{\"t\":3,\"r\":9252,\"x\":8.88,\"y\":89.7,\"ms\":5904},{\"t\":5,\"r\":9252},{\"t\":20,\"r\":9240,\"x\":0,\"y\":40},{\"t\":20,\"r\":9245,\"x\":8.88,\"y\":46.96},{\"t\":20,\"r\":9318,\"x\":14.06,\"y\":58.25},{\"t\":12},{\"t\":19,\"r\":9240,\"x\":21.27,\"y\":105.87},{\"t\":13},{\"t\":21,\"s\":21},{\"t\":1,\"l\":[9242,9262,9237,9323,9251,9568,9259]},{\"t\":20,\"r\":9262,\"x\":-15.67,\"y\":21.11},{\"t\":20,\"r\":9251,\"x\":16.39,\"y\":27.74},{\"t\":20,\"r\":9259,\"x\":14.64,\"y\":44.49},{\"t\":20,\"r\":9251,\"x\":5.39,\"y\":47.47},{\"t\":20,\"r\":9262,\"x\":-7.36,\"y\":53.44},{\"t\":8,\"x\":-4.16,\"y\":91.96},{\"t\":5,\"r\":9262},{\"t\":25},{\"t\":2,\"l\":[9245,9587,9265,9256,9271,9247,9615]},{\"t\":3,\"r\":9615,\"x\":2.25,\"y\":97.2,\"ms\":6054},{\"t\":21,\"s\":653},{\"t\":1,\"l\":[9251,9259,9257,9262,9323,9568,9237]},{\"t\":20,\"r\":9237,\"x\":25.71,\"y\":61.6},{\"t\":19,\"r\":9259,\"x\":13.62,\"y\":75.21},{\"t\":9},{\"t\":20,\"r\":9237,\"x\":-10.06,\"y\":67.28},{\"t\":8,\"x\":10.34,\"y\":61.67},{\"t\":9},{\"t\":20,\"r\":9237,\"x\":9.03,\"y\":20.89},{\"t\":20,\"r\":9262,\"x\":11.87,\"y\":28.68},{\"t\":20,\"r\":9259,\"x\":-9.26,\"y\":44.49},{\"t\":20,\"r\":9568,\"x\":-4.81,\"y\":52.64},{\"t\":20,\"r\":9237,\"x\":0.58,\"y\":50.09},{\"t\":20,\"r\":9259,\"x\":10.71,\"y\":59.92},{\"t\":20,\"r\":9568,\"x\":15.66,\"y\":73.61},{\"t\":22,\"r\":9323,\"x\":18.87,\"y\":103.68,\"s\":549},{\"t\":2,\"l\":[9265,9273,9252,9318,9256,9250,9240]},{\"t\":3,\"r\":9252,\"x\":-0.37,\"y\":92.33,\"ms\":4640},{\"t\":43},{\"t\":40,\"l\":[9273,9252,9318,9256,9250,9240,9271]},{\"t\":21,\"s\":495},{\"t\":1,\"l\":[9237,9247,9323,9568,9259,9242,9257]},{\"t\":20,\"r\":9237,\"x\":26.52,\"y\":45},{\"t\":20,\"r\":9247,\"x\":19.01,\"y\":44.85},{\"t\":20,\"r\":9237,\"x\":12.82,\"y\":40.77},{\"t\":20,\"r\":9247,\"x\":18.36,\"y\":44.92},{\"t\":20,\"r\":9568,\"x\":21.27,\"y\":53.15},{\"t\":20,\"r\":9237,\"x\":6.48,\"y\":45.29},{\"t\":19,\"r\":9323,\"x\":11.14,\"y\":53.88},{\"t\":15,\"s\":435},{\"t\":40,\"l\":[9247,9587,9256,9250,9245,9271,9615]},{\"t\":11},{\"t\":9},{\"t\":20,\"r\":9247,\"x\":3.13,\"y\":33.85},{\"t\":8,\"x\":14.28,\"y\":47.69},{\"t\":21,\"s\":372},{\"t\":1,\"l\":[9242,9323,9568,9257,9259,9262,9237]},{\"t\":20,\"r\":9237,\"x\":26.08,\"y\":59.56},{\"t\":8,\"x\":9.83,\"y\":94.95},{\"t\":11},{\"t\":21,\"s\":307},{\"t\":1,\"l\":[9247,9250,9256,9237,9257,9323,9568]},{\"t\":20,\"r\":9247,\"x\":25.93,\"y\":51.91},{\"t\":20,\"r\":9237,\"x\":13.62,\"y\":42.88},{\"t\":20,\"r\":9257,\"x\":-8.75,\"y\":48.78},{\"t\":20,\"r\":9568,\"x\":-15.09,\"y\":56.14},{\"t\":8,\"x\":-6.85,\"y\":64.07},{\"t\":21,\"s\":278},{\"t\":1,\"l\":[9242,9262,9237,9257,9323,9250,9318]},{\"t\":20,\"r\":9237,\"x\":25.64,\"y\":64.73},{\"t\":20,\"r\":9323,\"x\":22.22,\"y\":76.89},{\"t\":8,\"x\":5.61,\"y\":65.24},{\"t\":5,\"r\":9257},{\"t\":20,\"r\":9237,\"x\":1.09,\"y\":59.56},{\"t\":20,\"r\":9323,\"x\":8.01,\"y\":69.39},{\"t\":12},{\"t\":20,\"r\":9237,\"x\":16.1,\"y\":79.29},{\"t\":20,\"r\":9250,\"x\":8.01,\"y\":84.17},{\"t\":12},{\"t\":20,\"r\":9237,\"x\":1.31,\"y\":77.69},{\"t\":8,\"x\":24.69,\"y\":110.16},{\"t\":15,\"s\":175},{\"t\":40,\"l\":[9265,9615,9247,9271,9587,9245,9256]},{\"t\":11},{\"t\":13},{\"t\":21,\"s\":23},{\"t\":1,\"l\":[9323,9262,9568,9259,9237,9257,9242]},{\"t\":20,\"r\":9257,\"x\":1.45,\"y\":22.13},{\"t\":20,\"r\":9568,\"x\":4.51,\"y\":31.52},{\"t\":8,\"x\":-9.11,\"y\":93.2},{\"t\":26}]","updateMoment":"2021-08-15T01:25:56.835Z","blocks":9,"completionsNumer":177,"completionsDenom":197,"dLineBreaksNumer":6,"dLineBreaksDenom":9,"hucksNumer":6,"hucksDenom":8,"oLineHoldsNumer":12,"oLineHoldsDenom":30,"redZoneNumer":11,"redZoneDenom":13,"turnovers":20,"team_season_id":215}}